auto_code_review/__init__.py
auto_code_review/ai_analyzer.py
auto_code_review/cli.py
auto_code_review/core.py
auto_code_review/github_client.py
auto_code_review/utils.py
auto_code_review/prompts/prompt_template.jinja2
auto_code_review-0.1.5.dist-info/LICENSE.txt
auto_code_review-0.1.5.dist-info/METADATA
auto_code_review-0.1.5.dist-info/WHEEL
auto_code_review-0.1.5.dist-info/entry_points.txt
auto_code_review-0.1.5.dist-info/top_level.txt
auto_code_review-0.1.5.dist-info/RECORD
